{"Description":"","Valid":true,"Id":2396150,"LastModificationDate":"2018-10-31T10:53:31.413","LastRunDate":null,"MapType":"IntegrationServicesAdvancedMap","Name":"mapAccount","NetChange":true,"NetChangeFieldName":"SCRIBE_MODIFIEDON","ProcessDefinitionDbId":"2aff6765-13ce-4d58-a06d-325c94459e52","SourceConnectionId":"cb5f85fb-ed5a-4c4f-bac6-c1b11164e141","SourceConnectionName":"SFIntegration","SourceConnectionAlias":"SFIntegration","StartingBlockId":"3c0505c9-ea09-45e2-aaf4-ede11a35469f","SourceConnectionType":"Microsoft SQL Server","TargetConnections":[{"ConnectionAlias":"Salesforce","ConnectionId":"f579fd74-94e5-4bb4-b592-d53cd3830c01","ConnectionName":"Salesforce","ConnectionType":"Salesforce"}],"Version":"2.2","Blocks":[{"id":"3c0505c9-ea09-45e2-aaf4-ede11a35469f","blockType":"Query","category":"Source","name":"Account_Reverse","description":"","label":"Query Account_Reverse","originalBlockLabel":"Query","nextBlockId":"c1379281-337d-44e9-a32f-92fe3fefb1a3","parentBlockId":"","prevBlockId":"","x":352,"y":30,"entity":"Account_Reverse","actionName":"Query","connectionId":"cb5f85fb-ed5a-4c4f-bac6-c1b11164e141","filterItems":[],"relationships":[]},{"id":"c1379281-337d-44e9-a32f-92fe3fefb1a3","blockType":"ForEach","category":"Control","name":"ForEach","description":"","label":"For Each Result","originalBlockLabel":"For Each Result","nextBlockId":"","parentBlockId":"","prevBlockId":"3c0505c9-ea09-45e2-aaf4-ede11a35469f","firstChildBlockId":"6319423a-6a65-4fc0-8c47-3b7e1273eda4"},{"id":"6319423a-6a65-4fc0-8c47-3b7e1273eda4","blockType":"Update","category":"Target","name":"AccountUpdate","description":"","label":"Update Account","originalBlockLabel":"Update","nextBlockId":"","parentBlockId":"c1379281-337d-44e9-a32f-92fe3fefb1a3","prevBlockId":"","bulkCountPerOperation":2000,"useBulk":true,"entity":"Account","actionName":"Update","connectionId":"f579fd74-94e5-4bb4-b592-d53cd3830c01","isOnNoMatchMessage":true,"onNoMatchMessage":"Operation returned no results.  Label: [BLOCK LABEL], Name: [BLOCK NAME]","isOnErrorMessage":true,"onErrorMessage":"Operation failed.  Label: [BLOCK LABEL], Name: [BLOCK NAME], Message: [ORIGINAL MESSAGE]","filterItems":[{"compareValue":"Account_Reverse.Id","comparisonOperator":0,"fieldName":"Id","logicalOperator":0,"id":"52745eff-e53b-4171-9759-40d4379e2f05"}],"fieldMappings":[{"id":"612bb1df-d615-412e-953c-8399c42a42ab","targetDataType":"System.String","targetField":"FirstName","targetFormula":"Account_Reverse.FirstName","path":"Account"},{"id":"33ce6c80-4943-4225-9f0e-1f54b87923c5","targetDataType":"System.String","targetField":"LastName","targetFormula":"Account_Reverse.LastName","path":"Account"},{"id":"d3fd38d7-a3cf-4e57-8ae6-2148bfe7fad2","targetDataType":"System.String","targetField":"PersonMailingStreet","targetFormula":"Account_Reverse.PersonMailingStreet","path":"Account"},{"id":"7bc4b02e-a298-4a00-a9d4-79395f2c528e","targetDataType":"System.String","targetField":"PersonMailingPostalCode","targetFormula":"Account_Reverse.PersonMailingPostalCode","path":"Account"},{"id":"1eb81967-1ff4-4fdc-917d-3daf49788ef5","targetDataType":"System.String","targetField":"PersonMailingCity","targetFormula":"Account_Reverse.PersonMailingCity","path":"Account"},{"id":"5772a1a0-8079-48d5-93d0-d2220bfe4151","targetDataType":"System.String","targetField":"Region__c","targetFormula":"Account_Reverse.Region__c","path":"Account"},{"id":"7f209728-d845-40f9-abed-0fbcf0ecce92","targetDataType":"System.String","targetField":"PersonEmail","targetFormula":"Account_Reverse.PersonEmail","path":"Account"},{"id":"2e1cdd7d-156b-4ff1-8d42-55033d56c6c1","targetDataType":"System.String","targetField":"PersonHomePhone","targetFormula":"Account_Reverse.PersonHomePhone","path":"Account"},{"id":"4e03e57a-fa49-4794-954a-efe10ef70574","targetDataType":"System.String","targetField":"PersonMobilePhone","targetFormula":"Account_Reverse.PersonMobilePhone","path":"Account"},{"id":"b6b22976-c3fb-490b-a994-517c53f84252","targetDataType":"System.String","targetField":"PersonOtherPhone","targetFormula":"Account_Reverse.PersonOtherPhone","path":"Account"},{"id":"5dbe10a1-7f50-4ee0-9a4b-28c4ec58dd3a","targetDataType":"System.DateTime","targetField":"PersonBirthdate","targetFormula":"Account_Reverse.PersonBirthdate","path":"Account"},{"id":"6b3de14f-3d44-4020-af82-3108c747eab0","targetDataType":"System.String","targetField":"Gender__c","targetFormula":"Account_Reverse.Gender__c","path":"Account"},{"id":"a4095def-5fed-4d20-b505-4c2825304cda","targetDataType":"System.Boolean","targetField":"DoNotMail__c","targetFormula":"Account_Reverse.DoNotMail__c","path":"Account"},{"id":"e9c5c82a-1b6c-41c4-9d36-5b4c9c415e52","targetDataType":"System.Boolean","targetField":"DoNotCall__c","targetFormula":"Account_Reverse.DoNotCall__c","path":"Account"},{"id":"562c302a-ccfc-48d9-8b96-62f1bd1b518d","targetDataType":"System.Boolean","targetField":"DoNotSMS__c","targetFormula":"Account_Reverse.DoNotSMS__c","path":"Account"},{"id":"9168a7da-eca0-4ac5-bf1c-187e04648248","targetDataType":"System.Boolean","targetField":"PersonHasOptedOutOfEmail","targetFormula":"Account_Reverse.PersonHasOptedOutOfEmail","path":"Account"},{"id":"d7df75f1-6f82-460a-b9d0-f31c5243f6f5","targetDataType":"System.String","targetField":"SalesCenterBucket__c","targetFormula":"Account_Reverse.SalesCenterBucket__c","path":"Account"},{"id":"b09ae223-4a49-4859-9710-e92099f9580f","targetDataType":"System.Boolean","targetField":"ReadyForHappyCall__c","targetFormula":"Account_Reverse.ReadyForHappyCall__c","path":"Account"},{"id":"1dd0805d-b706-42e4-8347-4d155c309c9a","targetDataType":"System.Double","targetField":"NumberOfUnreachedHappyCalls__c","targetFormula":"Account_Reverse.NumberOfUnreachedHappyCalls__c","path":"Account"},{"id":"23f663f1-ada0-4efd-9ebd-b5e7083e548a","targetDataType":"System.Boolean","targetField":"HasHappyCallTask__c","targetFormula":"Account_Reverse.HasHappyCallTask__c","path":"Account"},{"id":"3ecf8a99-5307-41ee-9b83-4d5b6c885ab1","targetDataType":"System.Double","targetField":"AccountExternalId__c","targetFormula":"Account_Reverse.AccountExternalId__c","path":"Account"},{"id":"5b96b534-5bda-47d0-a2e9-71e0294a7491","targetDataType":"System.Boolean","targetField":"EmailOptOut__c","targetFormula":"Account_Reverse.EmailOptOut__c","path":"Account"}]}],"Revision":2,"RevisionDate":"2018-09-18T01:53:42.527","RevisionComment":null}